src/doc/background.md
src/doc/editing-ontologies.md
src/doc/facilityCobot-v022-core-cluster.svg
src/doc/python-api.md
src/doc/query-api.md
src/doc/rdf-and-types.md
src/doc/usd-framing.md
semantic/api/config.py
semantic/api/queries.py
semantic/api/semantic_api priorqueryrefacttor.py
semantic/api/semantic_api.py
semantic/api/semantic_api_orig.py
semantic/api/semantic_api_promised.py
semantic/api/semantic_client.py
semantic/api/semantic_client_orig.py
semantic/api/semantic_client_promised.py
semantic/common/common_types.py
semantic/common/query_utils.py
semantic/common/temporal_filter.py
semantic/common/utils.py
semantic/py_mqtt/py_mqtt.py
semantic/py_mqtt/py_mqtt_bu.py
semantic/py_mqtt/py_mqtt_orig.py
semantic/py_mqtt/py_mqtt_promised.py
semantic_api-0.0.35.dist-info/METADATA
semantic_api-0.0.35.dist-info/WHEEL
semantic_api-0.0.35.dist-info/licenses/LICENSE
semantic_api-0.0.35.dist-info/licenses/NOTICE
semantic_api-0.0.35.dist-info/RECORD
